MANIFEST.in
README.txt
setup.cfg
setup.py
docs/BUGS.txt
docs/CREDITS.txt
docs/HISTORY.txt
docs/INSTALL.txt
docs/LICENSE.GPL
docs/LICENSE.txt
enslyon/__init__.py
enslyon.existda.egg-info/PKG-INFO
enslyon.existda.egg-info/SOURCES.txt
enslyon.existda.egg-info/dependency_links.txt
enslyon.existda.egg-info/entry_points.txt
enslyon.existda.egg-info/namespace_packages.txt
enslyon.existda.egg-info/not-zip-safe
enslyon.existda.egg-info/requires.txt
enslyon.existda.egg-info/top_level.txt
enslyon/existda/ReXistDA.py
enslyon/existda/__init__.py
enslyon/existda/configure.zcml
enslyon/existda/eXistDA.py
enslyon/existda/eXistDAresult.py
enslyon/existda/eXistDAsyn.py
enslyon/existda/tests.py
enslyon/existda/utils.py
enslyon/existda/xslt.py
enslyon/existda/dtml/ReXistDAAdd.dtml
enslyon/existda/dtml/ReXistDAEdit.dtml
enslyon/existda/dtml/eXistDAAdd.dtml
enslyon/existda/dtml/eXistDAEdit.dtml
enslyon/existda/dtml/eXistDAsynAdd.dtml
enslyon/existda/dtml/eXistDAsynEdit.dtml
enslyon/existda/dtml/eXistMethodAdd.dtml
enslyon/existda/dtml/eXistMethodEdit.dtml
enslyon/existda/dtml/index_DA.dtml
enslyon/existda/dtml/index_RDA.dtml
enslyon/existda/dtml/index_method.dtml
enslyon/existda/dtml/index_syn.dtml
enslyon/existda/help/ReXistDA_add.stx
enslyon/existda/images/ReXistDA.png
enslyon/existda/images/eXistDA.png
enslyon/existda/images/eXistDAsyn.png
enslyon/existda/locales/fr/LC_MESSAGES/README.txt
enslyon/existda/profiles/default/metadata.xml