Metadata-Version: 1.1
Name: enslyon.existda
Version: 1.5
Summary: Connector to eXist XML Database
Home-page: https://bitbucket.org/pratic/enslyon.existda
Author: UNIS (ENS Lyon)
Author-email: unis@ens-lyon.fr
License: GPL
Platform: UNKNOWN
Classifier: Framework :: Plone
Classifier: Programming Language :: Python
